podcast_search/__init__.py
podcast_search-0.1.1.dist-info/WHEEL
podcast_search-0.1.1.dist-info/METADATA
podcast_search-0.1.1.dist-info/RECORD
