Metadata-Version: 2.1
Name: podcast_search
Version: 0.1.1
Summary: Let's find some podcasts!
Home-page: https://github.com/cryptojelmerkeuzenkamp
Author: Jelmer Keuzenkamp
Classifier: License :: OSI Approved :: MIT License
